LICENSE.txt
MANIFEST.in
README.rst
setup.cfg
setup.py
docs/images/candigLogin2.png
docs/images/example1.png
docs/images/example2.png
docs/images/filterFlowchart-2.png
docs/images/filterTable-2.png
docs/images/keycloakAdmin.png
docs/images/loginFlowchart.png
docs/images/loginWorkflow.png
tokenTracer/__init__.py
tokenTracer/assembler.py
tokenTracer/cmdparse.py
tokenTracer/display.py
tokenTracer/tracer.py
tokenTracer.egg-info/PKG-INFO
tokenTracer.egg-info/SOURCES.txt
tokenTracer.egg-info/dependency_links.txt
tokenTracer.egg-info/entry_points.txt
tokenTracer.egg-info/requires.txt
tokenTracer.egg-info/top_level.txt